cli.py
venues_config.py
models/__init__.py
models/event.py
models/venue.py
scrapers/__init__.py
scrapers/audio_nightclub.py
scrapers/base.py
scrapers/bimbos_365.py
scrapers/bottom_of_hill.py
scrapers/brick_mortar.py
scrapers/chapel.py
scrapers/gamh.py
scrapers/gray_area.py
scrapers/independent.py
scrapers/midway.py
scrapers/neck_woods.py
scrapers/public_works.py
scrapers/regency_ballroom.py
scrapers/reverb.py
scrapers/rickshaw_stop.py
scrapers/warfield.py
storage/__init__.py
storage/cache.py
storage/database.py
tests/__init__.py
tests/base.py
tests/base_venue.py
tests/dynamic_venue_tests.py
tests/run_tests.py
tests/test_pin_functionality.py
tests/test_pin_star_integration.py
tests/test_star_functionality.py
ui/__init__.py
ui/calendar.py
ui/colors.py
ui/terminal.py
utils/__init__.py
utils/parallel.py
utils/version_utils.py
sf_music_calendar-0.1.16.dist-info/METADATA
sf_music_calendar-0.1.16.dist-info/WHEEL
sf_music_calendar-0.1.16.dist-info/entry_points.txt
sf_music_calendar-0.1.16.dist-info/top_level.txt
sf_music_calendar-0.1.16.dist-info/RECORD
