Metadata-Version: 2.4
Name: sf-music-calendar
Version: 0.1.16
Summary: Multi-venue music event scraper for San Francisco
Author-email: Griffin Tarpenning <gtarpenning@gmail.com>
Requires-Python: >=3.9
Requires-Dist: requests>=2.31.0
Requires-Dist: beautifulsoup4>=4.12.0
Requires-Dist: rich>=13.0.0
Requires-Dist: lxml>=4.9.0
Requires-Dist: python-dateutil>=2.8.0
Provides-Extra: dev
Requires-Dist: black; extra == "dev"
Requires-Dist: pytest; extra == "dev"
Requires-Dist: build; extra == "dev"
Requires-Dist: twine; extra == "dev"
